kafka_schema_registry/__init__.py
kafka_schema_registry/version.py
kafka_schema_registry-0.1.2.dist-info/LICENSE
kafka_schema_registry-0.1.2.dist-info/METADATA
kafka_schema_registry-0.1.2.dist-info/WHEEL
kafka_schema_registry-0.1.2.dist-info/top_level.txt
kafka_schema_registry-0.1.2.dist-info/RECORD
