Metadata-Version: 2.1
Name: kafka-schema-registry
Version: 0.1.2
Summary: Kafka and schema registry integration
Home-page: https://github.com/flix-tech/kafka-schema-registry
Author: FlixTech
Author-email: open-source@flixbus.com
License: MIT
Project-URL: Changelog, https://github.com/flix-tech/kafka-schema-registry/blob/master/CHANGELOG.md
Project-URL: Source, https://github.com/flix-tech/kafka-schema-registry
Keywords: kafka schema-registry
Platform: UNKNOWN
Requires-Python: >=3.7
License-File: LICENSE
Requires-Dist: fastavro
Requires-Dist: kafka-python
Requires-Dist: requests
